other/gates.v
//SIMPLE GATES

`timescale 1ns/1ps

//AND GATE

module AND(

    output wire F,
    input wire A, B

    );

    wire X;

    nand nand_gate1(X, A, B);

    nand nand_gate2(F, X, X);

endmodule


//OR GATE

module OR(
    
    output wire F,
    input wire A,B
    
    );

    wire X;
    wire Y;

    nand nand_gate1(X, A, A);

    nand nand_gate2(Y, B, B);

    nand nand_gate3(F, X, Y);

endmodule

//XOR GATE

module XOR(

    output wire F,
    input wire A, B
    
    );

    wire X;
    wire Y;
    wire Z;

    nand nand_gate1(X, A, B);

    nand nand_gate2(Y, A, X);

    nand nand_gate3(Z, B, X);

    nand nand_gate4(F, Y, Z);

endmodule

//NOT GATE

module NOT(
    
    output wire F,
    input wire A

    );

    nand nand_gate1 (F, A, A);

endmodule


//8 BIT GATES

`timescale 1ns/1ps

//AND GATE

module AND8 (
    
    output wire [7:0] F,
    input wire [7:0] A, B
    
    );

    AND AND0 (F[0], A[0], B[0]);
    AND AND1 (F[1], A[1], B[1]);
    AND AND2 (F[2], A[2], B[2]);
    AND AND3 (F[3], A[3], B[3]);
    AND AND4 (F[4], A[4], B[4]);
    AND AND5 (F[5], A[5], B[5]);
    AND AND6 (F[6], A[6], B[6]);
    AND AND7 (F[7], A[7], B[7]);

endmodule


//OR GATE

module OR8 (
    
    output wire [7:0] F,
    input wire [7:0] A, B
    
    );

    OR OR0 (F[0], A[0], B[0]);
    OR OR1 (F[1], A[1], B[1]);
    OR OR2 (F[2], A[2], B[2]);
    OR OR3 (F[3], A[3], B[3]);
    OR OR4 (F[4], A[4], B[4]);
    OR OR5 (F[5], A[5], B[5]);
    OR OR6 (F[6], A[6], B[6]);
    OR OR7 (F[7], A[7], B[7]);
    
endmodule


//XOR GATE

module XOR8 (
    
    output wire [7:0] F,
    input wire [7:0] A, B
    
    );

    XOR XOR0 (F[0], A[0], B[0]);
    XOR XOR1 (F[1], A[1], B[1]);
    XOR XOR2 (F[2], A[2], B[2]);
    XOR XOR3 (F[3], A[3], B[3]);
    XOR XOR4 (F[4], A[4], B[4]);
    XOR XOR5 (F[5], A[5], B[5]);
    XOR XOR6 (F[6], A[6], B[6]);
    XOR XOR7 (F[7], A[7], B[7]);

endmodule


//NOT GATE

module NOT8 (
    
    output wire [7:0] F,
    input wire [7:0] A
    
    );

   NOT NOT0 (F[0], A[0]);
   NOT NOT1 (F[1], A[1]);
   NOT NOT2 (F[2], A[2]);
   NOT NOT3 (F[3], A[3]);
   NOT NOT4 (F[4], A[4]);
   NOT NOT5 (F[5], A[5]);
   NOT NOT6 (F[6], A[6]);
   NOT NOT7 (F[7], A[7]);

endmodule

other/components.v
/*
Components File:
Created because of the need to have a file that contains all the components used in the design.
Simultaneous imports of the base gates and components give include errors. This file is used to import all the components in one go.
*/

`timescale 1ns/1ps
`include "gates.v"

/*-----------------------------------------------ARITHMETIC COMPONENTS-----------------------------------------------*/

module HALFADDER(

    output wire Carry, Sum,
    input wire A, B

    );

    XOR XOR1 (Sum, A, B);
    AND AND1 (Carry, A, B);

endmodule


module FULLADDER(

    output wire Carry, Sum,
    input wire A, B, Cin

    );

    wire C1, S1, C2;

    HALFADDER HA1 (C1, S1, A, B);
    HALFADDER HA2 (C2, Sum, S1, Cin);
    
    OR OR1 (Carry, C1, C2);

endmodule


module RIPPLECARRY(
    
    output wire Carry,
    output wire [7:0] Sum,
    input wire [7:0] A, B, 
    input wire Cin
    
    );

    wire C0, C1, C2, C3, C4, C5, C6;

    FULLADDER FA0 (C0, Sum[0], A[0], B[0], Cin);
    FULLADDER FA1 (C1, Sum[1], A[1], B[1], C0);
    FULLADDER FA2 (C2, Sum[2], A[2], B[2], C1);
    FULLADDER FA3 (C3, Sum[3], A[3], B[3], C2);
    FULLADDER FA4 (C4, Sum[4], A[4], B[4], C3);
    FULLADDER FA5 (C5, Sum[5], A[5], B[5], C4);
    FULLADDER FA6 (C6, Sum[6], A[6], B[6], C5);
    FULLADDER FA7 (Carry, Sum[7], A[7], B[7], C6);

endmodule


module EQUAL_ZERO(

    output wire F,
    input wire [7:0] A

    );

    wire X1, X2, X3, X4;
    wire X5, X6;
    wire X7;

    OR or_gate01(X1, A[0],  A[1]);
    OR or_gate02(X2, A[2],  A[3]);
    OR or_gate03(X3, A[4],  A[5]);
    OR or_gate04(X4, A[6],  A[7]);

    OR or_gate09(X5,  X1, X2);
    OR or_gate10(X6, X3, X4);

    OR or_gate13(X7, X5, X6);

    NOT not_gate1(F, X7);

endmodule


module LESS_ZERO(

    output wire F,
    input wire [7:0] A

    );

    OR or_gate1(F, A[7], 1'b0);

endmodule


module OVERFLOW_ADD(

    output wire F,
    input wire A, B, R

    );

    wire nA, nB, nR;
    wire andAB, andnAB;
    wire aux1, aux2;

    NOT NOT0 (nA, A);
    NOT NOT1 (nB, B);
    NOT NOT2 (nR, R);

    AND AND0 (andAB, A, B);
    AND AND1 (andnAB, nA, nB);

    AND AND2 (aux1, andAB, nR);
    AND AND3 (aux2, andnAB, R);

    OR OR0 (F, aux1, aux2);

endmodule


module OVERFLOW_SUB(

    output wire F,
    input wire A, B, R

    );

    wire nA, nB, nR;
    wire andBR, andnBR;
    wire aux1, aux2;

    NOT NOT0 (nA, A);
    NOT NOT1 (nB, B);
    NOT NOT2 (nR, R);

    AND AND0 (andBR, B, R);
    AND AND1 (andnBR, nB, nR);

    AND AND2 (aux1, A, andnBR);
    AND AND3 (aux2, nA, andBR);

    OR OR0 (F, aux1, aux2);

endmodule

/*-----------------------------------------------MULTIPLEXERS-----------------------------------------------*/

module MUX2_1(
    
    output wire [7:0] F,
    input wire S,
    input wire [7:0] A, B
    
    );

    wire nS;
    wire [7:0] wA, wB;

    NOT NOT0 (nS, S);

    AND AND0 (wA[0], A[0], nS);
    AND AND1 (wA[1], A[1], nS);
    AND AND2 (wA[2], A[2], nS);
    AND AND3 (wA[3], A[3], nS);
    AND AND4 (wA[4], A[4], nS);
    AND AND5 (wA[5], A[5], nS);
    AND AND6 (wA[6], A[6], nS);
    AND AND7 (wA[7], A[7], nS);

    AND AND8 (wB[0], B[0], S);
    AND AND9 (wB[1], B[1], S);
    AND AND10 (wB[2], B[2], S);
    AND AND11 (wB[3], B[3], S);
    AND AND12 (wB[4], B[4], S);
    AND AND13 (wB[5], B[5], S);
    AND AND14 (wB[6], B[6], S);
    AND AND15 (wB[7], B[7], S);

    OR8 OR0 (F, wA, wB);

endmodule


module MUX2_1_classic (
    
    output wire F,
    input wire S,
    input wire A, B
    
    );

    wire nS;
    wire wA, wB;

    NOT NOT0 (nS, S);

    AND AND0 (wA, A, nS);
    AND AND1 (wB, B, S);

    OR OR0 (F, wA, wB);

endmodule


module MUX4_1 (
    
    output wire [7:0] F,
    input wire [1:0] S,
    input wire [7:0] A, B, C, D
    
    );

    wire nS0, nS1;
    wire N0, N1, N2, N3;
    wire [7:0] M0, M1, M2, M3;
    wire [7:0] L0, L1;

    NOT NOT0 (nS0, S[0]);
    NOT NOT1 (nS1, S[1]);

    AND AND0 (N0, nS0, nS1);
    AND AND1 (N1, S[0], nS1);
    AND AND2 (N2, nS0, S[1]);
    AND AND3 (N3, S[0], S[1]);

    AND AND4 (M0[0], A[0], N0);
    AND AND5 (M0[1], A[1], N0);
    AND AND6 (M0[2], A[2], N0);
    AND AND7 (M0[3], A[3], N0);
    AND AND8 (M0[4], A[4], N0);
    AND AND9 (M0[5], A[5], N0);
    AND AND10 (M0[6], A[6], N0);
    AND AND11 (M0[7], A[7], N0);

    AND AND12 (M1[0], B[0], N1);
    AND AND13 (M1[1], B[1], N1);
    AND AND14 (M1[2], B[2], N1);
    AND AND15 (M1[3], B[3], N1);
    AND AND16 (M1[4], B[4], N1);
    AND AND17 (M1[5], B[5], N1);
    AND AND18 (M1[6], B[6], N1);
    AND AND19 (M1[7], B[7], N1);

    AND AND20 (M2[0], C[0], N2);
    AND AND21 (M2[1], C[1], N2);
    AND AND22 (M2[2], C[2], N2);
    AND AND23 (M2[3], C[3], N2);
    AND AND24 (M2[4], C[4], N2);
    AND AND25 (M2[5], C[5], N2);
    AND AND26 (M2[6], C[6], N2);
    AND AND27 (M2[7], C[7], N2);
    
    AND AND28 (M3[0], D[0], N3);
    AND AND29 (M3[1], D[1], N3);
    AND AND30 (M3[2], D[2], N3);
    AND AND31 (M3[3], D[3], N3);
    AND AND32 (M3[4], D[4], N3);
    AND AND33 (M3[5], D[5], N3);
    AND AND34 (M3[6], D[6], N3);
    AND AND35 (M3[7], D[7], N3);
    
    OR8 OR1 (L0, M0, M1);
    OR8 OR2 (L1, M2, M3);

    OR8 OR3 (F, L0, L1);

endmodule


module MUX4_1_classic (
    
    output wire F,
    input wire [1:0] S,
    input wire A, B, C, D
    
    );

    wire nS0, nS1;
    wire N0, N1, N2, N3;
    wire M0, M1, M2, M3;
    wire L0, L1;

    NOT NOT0 (nS0, S[0]);
    NOT NOT1 (nS1, S[1]);

    AND AND0 (N0, nS0, nS1);
    AND AND1 (N1, S[0], nS1);
    AND AND2 (N2, nS0, S[1]);
    AND AND3 (N3, S[0], S[1]);

    AND AND4 (M0, A, N0);
    AND AND5 (M1, B, N1);
    AND AND6 (M2, C, N2);
    AND AND7 (M3, D, N3);

    OR OR0 (L0, M0, M1);
    OR OR1 (L1, M2, M3);

    OR OR2 (F, L0, L1);

endmodule

/*-----------------------------------------------ARITHMETIC UNIT-----------------------------------------------*/

module AU(

    output wire Carry,
    output wire [7:0] Result,
    input wire [7:0] A, B,
    input wire [1:0] Control

    );

    wire [7:0] Sum, Increment, Subtraction, Decrement;
    wire sumCarry, incCarry, subCarry, nsubCarry, ndecCarry, decCarry;
    wire [7:0] nB;

    NOT8 NOT0 (nB, B);
    NOT NOT1 (nsubCarry, subCarry);
    NOT NOT2 (ndecCarry, decCarry);

    RIPPLECARRY RC0 (sumCarry, Sum, A, B, 1'b0);
    RIPPLECARRY RC1 (incCarry, Increment, A, 8'b00000001, 1'b0);
    RIPPLECARRY RC2 (subCarry, Subtraction, A, nB, 1'b1);
    RIPPLECARRY RC3 (decCarry, Decrement, A, 8'b11111111, 1'b0);

    MUX4_1 MUX0 (Result, Control, Sum, Increment, Subtraction, Decrement);
    MUX4_1_classic MUX1 (Carry, Control, sumCarry, incCarry, nsubCarry, ndecCarry);

endmodule

/*-----------------------------------------------LOGIC UNIT-----------------------------------------------*/

module LU(

    output wire [7:0] F,
    input wire [7:0] A, B,
    input wire [1:0] Control

    );

    wire [7:0] And, Or, Xor, Not;

    AND8 AND0 (And, A, B);
    OR8 OR0 (Or, A, B);
    XOR8 XOR0 (Xor, A, B);
    NOT8 NOT0 (Not, A);

    MUX4_1 MUX0 (F, Control, And, Or, Xor, Not);

endmodule

other/testbenches/LTZ_TB.v
//LESS THAN ZERO TESTBENCH

`timescale 1ns/1ps
`include "components.v"

module LESS_ZERO_TB();

    reg [7:0] A_TB;
    wire F_TB;

    integer i;

    LESS_ZERO DUT(F_TB, A_TB);

    initial 
    
        begin
        
            $dumpfile("LESS_ZERO_TB.vcd");
            $dumpvars(0, LESS_ZERO_TB);

            for (i = 0; i < 100; i = i + 1) begin

                A_TB = i;

                #10;

            end

        end

endmodule

other/waveforms/LESS_ZERO_TB.vcd
$date
	Sun Jun  2 17:57:52 2024
$end
$version
	Icarus Verilog
$end
$timescale
	1ps
$end
$scope module LESS_ZERO_TB $end
$var wire 1 ! F_TB $end
$var reg 8 " A_TB [7:0] $end
$var integer 32 # i [31:0] $end
$scope module DUT $end
$var wire 8 $ A [7:0] $end
$var wire 1 ! F $end
$scope module or_gate1 $end
$var wire 1 % A $end
$var wire 1 & B $end
$var wire 1 ! F $end
$var wire 1 ' X $end
$var wire 1 ( Y $end
$upscope $end
$upscope $end
$upscope $end
$enddefinitions $end
$comment Show the parameter values. $end
$dumpall
$end
#0
$dumpvars
1(
1'
0&
0%
b0 $
b0 #
b0 "
0!
$end
#10000
b1 "
b1 $
b1 #
#20000
b10 "
b10 $
b10 #
#30000
b11 "
b11 $
b11 #
#40000
b100 "
b100 $
b100 #
#50000
b101 "
b101 $
b101 #
#60000
b110 "
b110 $
b110 #
#70000
b111 "
b111 $
b111 #
#80000
b1000 "
b1000 $
b1000 #
#90000
b1001 "
b1001 $
b1001 #
#100000
b1010 "
b1010 $
b1010 #
#110000
b1011 "
b1011 $
b1011 #
#120000
b1100 "
b1100 $
b1100 #
#130000
b1101 "
b1101 $
b1101 #
#140000
b1110 "
b1110 $
b1110 #
#150000
b1111 "
b1111 $
b1111 #
#160000
b10000 "
b10000 $
b10000 #
#170000
b10001 "
b10001 $
b10001 #
#180000
b10010 "
b10010 $
b10010 #
#190000
b10011 "
b10011 $
b10011 #
#200000
b10100 "
b10100 $
b10100 #
#210000
b10101 "
b10101 $
b10101 #
#220000
b10110 "
b10110 $
b10110 #
#230000
b10111 "
b10111 $
b10111 #
#240000
b11000 "
b11000 $
b11000 #
#250000
b11001 "
b11001 $
b11001 #
#260000
b11010 "
b11010 $
b11010 #
#270000
b11011 "
b11011 $
b11011 #
#280000
b11100 "
b11100 $
b11100 #
#290000
b11101 "
b11101 $
b11101 #
#300000
b11110 "
b11110 $
b11110 #
#310000
b11111 "
b11111 $
b11111 #
#320000
b100000 "
b100000 $
b100000 #
#330000
b100001 "
b100001 $
b100001 #
#340000
b100010 "
b100010 $
b100010 #
#350000
b100011 "
b100011 $
b100011 #
#360000
b100100 "
b100100 $
b100100 #
#370000
b100101 "
b100101 $
b100101 #
#380000
b100110 "
b100110 $
b100110 #
#390000
b100111 "
b100111 $
b100111 #
#400000
b101000 "
b101000 $
b101000 #
#410000
b101001 "
b101001 $
b101001 #
#420000
b101010 "
b101010 $
b101010 #
#430000
b101011 "
b101011 $
b101011 #
#440000
b101100 "
b101100 $
b101100 #
#450000
b101101 "
b101101 $
b101101 #
#460000
b101110 "
b101110 $
b101110 #
#470000
b101111 "
b101111 $
b101111 #
#480000
b110000 "
b110000 $
b110000 #
#490000
b110001 "
b110001 $
b110001 #
#500000
b110010 "
b110010 $
b110010 #
#510000
b110011 "
b110011 $
b110011 #
#520000
b110100 "
b110100 $
b110100 #
#530000
b110101 "
b110101 $
b110101 #
#540000
b110110 "
b110110 $
b110110 #
#550000
b110111 "
b110111 $
b110111 #
#560000
b111000 "
b111000 $
b111000 #
#570000
b111001 "
b111001 $
b111001 #
#580000
b111010 "
b111010 $
b111010 #
#590000
b111011 "
b111011 $
b111011 #
#600000
b111100 "
b111100 $
b111100 #
#610000
b111101 "
b111101 $
b111101 #
#620000
b111110 "
b111110 $
b111110 #
#630000
b111111 "
b111111 $
b111111 #
#640000
b1000000 "
b1000000 $
b1000000 #
#650000
b1000001 "
b1000001 $
b1000001 #
#660000
b1000010 "
b1000010 $
b1000010 #
#670000
b1000011 "
b1000011 $
b1000011 #
#680000
b1000100 "
b1000100 $
b1000100 #
#690000
b1000101 "
b1000101 $
b1000101 #
#700000
b1000110 "
b1000110 $
b1000110 #
#710000
b1000111 "
b1000111 $
b1000111 #
#720000
b1001000 "
b1001000 $
b1001000 #
#730000
b1001001 "
b1001001 $
b1001001 #
#740000
b1001010 "
b1001010 $
b1001010 #
#750000
b1001011 "
b1001011 $
b1001011 #
#760000
b1001100 "
b1001100 $
b1001100 #
#770000
b1001101 "
b1001101 $
b1001101 #
#780000
b1001110 "
b1001110 $
b1001110 #
#790000
b1001111 "
b1001111 $
b1001111 #
#800000
b1010000 "
b1010000 $
b1010000 #
#810000
b1010001 "
b1010001 $
b1010001 #
#820000
b1010010 "
b1010010 $
b1010010 #
#830000
b1010011 "
b1010011 $
b1010011 #
#840000
b1010100 "
b1010100 $
b1010100 #
#850000
b1010101 "
b1010101 $
b1010101 #
#860000
b1010110 "
b1010110 $
b1010110 #
#870000
b1010111 "
b1010111 $
b1010111 #
#880000
b1011000 "
b1011000 $
b1011000 #
#890000
b1011001 "
b1011001 $
b1011001 #
#900000
b1011010 "
b1011010 $
b1011010 #
#910000
b1011011 "
b1011011 $
b1011011 #
#920000
b1011100 "
b1011100 $
b1011100 #
#930000
b1011101 "
b1011101 $
b1011101 #
#940000
b1011110 "
b1011110 $
b1011110 #
#950000
b1011111 "
b1011111 $
b1011111 #
#960000
b1100000 "
b1100000 $
b1100000 #
#970000
b1100001 "
b1100001 $
b1100001 #
#980000
b1100010 "
b1100010 $
b1100010 #
#990000
b1100011 "
b1100011 $
b1100011 #
#1000000
b1100100 #
