other/gates.v
//SIMPLE GATES

`timescale 1ns/1ps

//AND GATE

module AND(

    output wire F,
    input wire A, B

    );

    wire X;

    nand nand_gate1(X, A, B);

    nand nand_gate2(F, X, X);

endmodule


//OR GATE

module OR(
    
    output wire F,
    input wire A,B
    
    );

    wire X;
    wire Y;

    nand nand_gate1(X, A, A);

    nand nand_gate2(Y, B, B);

    nand nand_gate3(F, X, Y);

endmodule

//XOR GATE

module XOR(

    output wire F,
    input wire A, B
    
    );

    wire X;
    wire Y;
    wire Z;

    nand nand_gate1(X, A, B);

    nand nand_gate2(Y, A, X);

    nand nand_gate3(Z, B, X);

    nand nand_gate4(F, Y, Z);

endmodule

//NOT GATE

module NOT(
    
    output wire F,
    input wire A

    );

    nand nand_gate1 (F, A, A);

endmodule


//8 BIT GATES

`timescale 1ns/1ps

//AND GATE

module AND8 (
    
    output wire [7:0] F,
    input wire [7:0] A, B
    
    );

    AND AND0 (F[0], A[0], B[0]);
    AND AND1 (F[1], A[1], B[1]);
    AND AND2 (F[2], A[2], B[2]);
    AND AND3 (F[3], A[3], B[3]);
    AND AND4 (F[4], A[4], B[4]);
    AND AND5 (F[5], A[5], B[5]);
    AND AND6 (F[6], A[6], B[6]);
    AND AND7 (F[7], A[7], B[7]);

endmodule


//OR GATE

module OR8 (
    
    output wire [7:0] F,
    input wire [7:0] A, B
    
    );

    OR OR0 (F[0], A[0], B[0]);
    OR OR1 (F[1], A[1], B[1]);
    OR OR2 (F[2], A[2], B[2]);
    OR OR3 (F[3], A[3], B[3]);
    OR OR4 (F[4], A[4], B[4]);
    OR OR5 (F[5], A[5], B[5]);
    OR OR6 (F[6], A[6], B[6]);
    OR OR7 (F[7], A[7], B[7]);
    
endmodule


//XOR GATE

module XOR8 (
    
    output wire [7:0] F,
    input wire [7:0] A, B
    
    );

    XOR XOR0 (F[0], A[0], B[0]);
    XOR XOR1 (F[1], A[1], B[1]);
    XOR XOR2 (F[2], A[2], B[2]);
    XOR XOR3 (F[3], A[3], B[3]);
    XOR XOR4 (F[4], A[4], B[4]);
    XOR XOR5 (F[5], A[5], B[5]);
    XOR XOR6 (F[6], A[6], B[6]);
    XOR XOR7 (F[7], A[7], B[7]);

endmodule


//NOT GATE

module NOT8 (
    
    output wire [7:0] F,
    input wire [7:0] A
    
    );

   NOT NOT0 (F[0], A[0]);
   NOT NOT1 (F[1], A[1]);
   NOT NOT2 (F[2], A[2]);
   NOT NOT3 (F[3], A[3]);
   NOT NOT4 (F[4], A[4]);
   NOT NOT5 (F[5], A[5]);
   NOT NOT6 (F[6], A[6]);
   NOT NOT7 (F[7], A[7]);

endmodule

other/components.v
/*
Components File:
Created because of the need to have a file that contains all the components used in the design.
Simultaneous imports of the base gates and components give include errors. This file is used to import all the components in one go.
*/

`timescale 1ns/1ps
`include "gates.v"

/*-----------------------------------------------ARITHMETIC COMPONENTS-----------------------------------------------*/

module HALFADDER(

    output wire Carry, Sum,
    input wire A, B

    );

    XOR XOR1 (Sum, A, B);
    AND AND1 (Carry, A, B);

endmodule


module FULLADDER(

    output wire Carry, Sum,
    input wire A, B, Cin

    );

    wire C1, S1, C2;

    HALFADDER HA1 (C1, S1, A, B);
    HALFADDER HA2 (C2, Sum, S1, Cin);
    
    OR OR1 (Carry, C1, C2);

endmodule


module RIPPLECARRY(
    
    output wire Carry,
    output wire [7:0] Sum,
    input wire [7:0] A, B, 
    input wire Cin
    
    );

    wire C0, C1, C2, C3, C4, C5, C6;

    FULLADDER FA0 (C0, Sum[0], A[0], B[0], Cin);
    FULLADDER FA1 (C1, Sum[1], A[1], B[1], C0);
    FULLADDER FA2 (C2, Sum[2], A[2], B[2], C1);
    FULLADDER FA3 (C3, Sum[3], A[3], B[3], C2);
    FULLADDER FA4 (C4, Sum[4], A[4], B[4], C3);
    FULLADDER FA5 (C5, Sum[5], A[5], B[5], C4);
    FULLADDER FA6 (C6, Sum[6], A[6], B[6], C5);
    FULLADDER FA7 (Carry, Sum[7], A[7], B[7], C6);

endmodule


module EQUAL_ZERO(

    output wire F,
    input wire [7:0] A

    );

    wire X1, X2, X3, X4;
    wire X5, X6;
    wire X7;

    OR or_gate01(X1, A[0],  A[1]);
    OR or_gate02(X2, A[2],  A[3]);
    OR or_gate03(X3, A[4],  A[5]);
    OR or_gate04(X4, A[6],  A[7]);

    OR or_gate09(X5,  X1, X2);
    OR or_gate10(X6, X3, X4);

    OR or_gate13(X7, X5, X6);

    NOT not_gate1(F, X7);

endmodule


module LESS_ZERO(

    output wire F,
    input wire [7:0] A

    );

    OR or_gate1(F, A[7], 1'b0);

endmodule


module OVERFLOW_ADD(

    output wire F,
    input wire A, B, R

    );

    wire nA, nB, nR;
    wire andAB, andnAB;
    wire aux1, aux2;

    NOT NOT0 (nA, A);
    NOT NOT1 (nB, B);
    NOT NOT2 (nR, R);

    AND AND0 (andAB, A, B);
    AND AND1 (andnAB, nA, nB);

    AND AND2 (aux1, andAB, nR);
    AND AND3 (aux2, andnAB, R);

    OR OR0 (F, aux1, aux2);

endmodule


module OVERFLOW_SUB(

    output wire F,
    input wire A, B, R

    );

    wire nA, nB, nR;
    wire andBR, andnBR;
    wire aux1, aux2;

    NOT NOT0 (nA, A);
    NOT NOT1 (nB, B);
    NOT NOT2 (nR, R);

    AND AND0 (andBR, B, R);
    AND AND1 (andnBR, nB, nR);

    AND AND2 (aux1, A, andnBR);
    AND AND3 (aux2, nA, andBR);

    OR OR0 (F, aux1, aux2);

endmodule

/*-----------------------------------------------MULTIPLEXERS-----------------------------------------------*/

module MUX2_1(
    
    output wire [7:0] F,
    input wire S,
    input wire [7:0] A, B
    
    );

    wire nS;
    wire [7:0] wA, wB;

    NOT NOT0 (nS, S);

    AND AND0 (wA[0], A[0], nS);
    AND AND1 (wA[1], A[1], nS);
    AND AND2 (wA[2], A[2], nS);
    AND AND3 (wA[3], A[3], nS);
    AND AND4 (wA[4], A[4], nS);
    AND AND5 (wA[5], A[5], nS);
    AND AND6 (wA[6], A[6], nS);
    AND AND7 (wA[7], A[7], nS);

    AND AND8 (wB[0], B[0], S);
    AND AND9 (wB[1], B[1], S);
    AND AND10 (wB[2], B[2], S);
    AND AND11 (wB[3], B[3], S);
    AND AND12 (wB[4], B[4], S);
    AND AND13 (wB[5], B[5], S);
    AND AND14 (wB[6], B[6], S);
    AND AND15 (wB[7], B[7], S);

    OR8 OR0 (F, wA, wB);

endmodule


module MUX2_1_classic (
    
    output wire F,
    input wire S,
    input wire A, B
    
    );

    wire nS;
    wire wA, wB;

    NOT NOT0 (nS, S);

    AND AND0 (wA, A, nS);
    AND AND1 (wB, B, S);

    OR OR0 (F, wA, wB);

endmodule


module MUX4_1 (
    
    output wire [7:0] F,
    input wire [1:0] S,
    input wire [7:0] A, B, C, D
    
    );

    wire nS0, nS1;
    wire N0, N1, N2, N3;
    wire [7:0] M0, M1, M2, M3;
    wire [7:0] L0, L1;

    NOT NOT0 (nS0, S[0]);
    NOT NOT1 (nS1, S[1]);

    AND AND0 (N0, nS0, nS1);
    AND AND1 (N1, S[0], nS1);
    AND AND2 (N2, nS0, S[1]);
    AND AND3 (N3, S[0], S[1]);

    AND AND4 (M0[0], A[0], N0);
    AND AND5 (M0[1], A[1], N0);
    AND AND6 (M0[2], A[2], N0);
    AND AND7 (M0[3], A[3], N0);
    AND AND8 (M0[4], A[4], N0);
    AND AND9 (M0[5], A[5], N0);
    AND AND10 (M0[6], A[6], N0);
    AND AND11 (M0[7], A[7], N0);

    AND AND12 (M1[0], B[0], N1);
    AND AND13 (M1[1], B[1], N1);
    AND AND14 (M1[2], B[2], N1);
    AND AND15 (M1[3], B[3], N1);
    AND AND16 (M1[4], B[4], N1);
    AND AND17 (M1[5], B[5], N1);
    AND AND18 (M1[6], B[6], N1);
    AND AND19 (M1[7], B[7], N1);

    AND AND20 (M2[0], C[0], N2);
    AND AND21 (M2[1], C[1], N2);
    AND AND22 (M2[2], C[2], N2);
    AND AND23 (M2[3], C[3], N2);
    AND AND24 (M2[4], C[4], N2);
    AND AND25 (M2[5], C[5], N2);
    AND AND26 (M2[6], C[6], N2);
    AND AND27 (M2[7], C[7], N2);
    
    AND AND28 (M3[0], D[0], N3);
    AND AND29 (M3[1], D[1], N3);
    AND AND30 (M3[2], D[2], N3);
    AND AND31 (M3[3], D[3], N3);
    AND AND32 (M3[4], D[4], N3);
    AND AND33 (M3[5], D[5], N3);
    AND AND34 (M3[6], D[6], N3);
    AND AND35 (M3[7], D[7], N3);
    
    OR8 OR1 (L0, M0, M1);
    OR8 OR2 (L1, M2, M3);

    OR8 OR3 (F, L0, L1);

endmodule


module MUX4_1_classic (
    
    output wire F,
    input wire [1:0] S,
    input wire A, B, C, D
    
    );

    wire nS0, nS1;
    wire N0, N1, N2, N3;
    wire M0, M1, M2, M3;
    wire L0, L1;

    NOT NOT0 (nS0, S[0]);
    NOT NOT1 (nS1, S[1]);

    AND AND0 (N0, nS0, nS1);
    AND AND1 (N1, S[0], nS1);
    AND AND2 (N2, nS0, S[1]);
    AND AND3 (N3, S[0], S[1]);

    AND AND4 (M0, A, N0);
    AND AND5 (M1, B, N1);
    AND AND6 (M2, C, N2);
    AND AND7 (M3, D, N3);

    OR OR0 (L0, M0, M1);
    OR OR1 (L1, M2, M3);

    OR OR2 (F, L0, L1);

endmodule

/*-----------------------------------------------ARITHMETIC UNIT-----------------------------------------------*/

module AU(

    output wire Carry,
    output wire [7:0] Result,
    input wire [7:0] A, B,
    input wire [1:0] Control

    );

    wire [7:0] Sum, Increment, Subtraction, Decrement;
    wire sumCarry, incCarry, subCarry, nsubCarry, ndecCarry, decCarry;
    wire [7:0] nB;

    NOT8 NOT0 (nB, B);
    NOT NOT1 (nsubCarry, subCarry);
    NOT NOT2 (ndecCarry, decCarry);

    RIPPLECARRY RC0 (sumCarry, Sum, A, B, 1'b0);
    RIPPLECARRY RC1 (incCarry, Increment, A, 8'b00000001, 1'b0);
    RIPPLECARRY RC2 (subCarry, Subtraction, A, nB, 1'b1);
    RIPPLECARRY RC3 (decCarry, Decrement, A, 8'b11111111, 1'b0);

    MUX4_1 MUX0 (Result, Control, Sum, Increment, Subtraction, Decrement);
    MUX4_1_classic MUX1 (Carry, Control, sumCarry, incCarry, nsubCarry, ndecCarry);

endmodule

/*-----------------------------------------------LOGIC UNIT-----------------------------------------------*/

module LU(

    output wire [7:0] F,
    input wire [7:0] A, B,
    input wire [1:0] Control

    );

    wire [7:0] And, Or, Xor, Not;

    AND8 AND0 (And, A, B);
    OR8 OR0 (Or, A, B);
    XOR8 XOR0 (Xor, A, B);
    NOT8 NOT0 (Not, A);

    MUX4_1 MUX0 (F, Control, And, Or, Xor, Not);

endmodule

other/testbenches/RIPPLECARRY_TB.v
//RIPPLECARRY ADDER TESTBENCH

`timescale 1ns/1ps
`include "components.v"

module RIPPLECARRY_TB();

    reg [7:0] A_TB;
    reg [7:0] B_TB;
    reg C_TB;
    wire [7:0] F_TB;
    wire E_TB;

    integer i, j;

    RIPPLECARRY DUT(E_TB, F_TB, A_TB, B_TB, C_TB);

    initial

        begin
            
            $dumpfile("RIPPLECARRY_TB.vcd");
            $dumpvars(0, RIPPLECARRY_TB);

            for (i = 0; i < 32; i = i + 1) begin

                for (j = 0; j < 32; j = j + 1) begin

                        A_TB = i;
                        B_TB = j;

                        C_TB = 0;

                        #10;

                        C_TB = 1;

                        #10;
                    
                end
                
            end
        
        end

endmodule

other/waveforms/RIPPLECARRY_TB.vcd
$date
	Sun Jun  2 17:52:30 2024
$end
$version
	Icarus Verilog
$end
$timescale
	1ps
$end
$scope module RIPPLECARRY_TB $end
$var wire 8 ! F_TB [7:0] $end
$var wire 1 " E_TB $end
$var reg 8 # A_TB [7:0] $end
$var reg 8 $ B_TB [7:0] $end
$var reg 1 % C_TB $end
$var integer 32 & i [31:0] $end
$var integer 32 ' j [31:0] $end
$scope module DUT $end
$var wire 8 ( A [7:0] $end
$var wire 8 ) B [7:0] $end
$var wire 1 % Cin $end
$var wire 8 * Sum [7:0] $end
$var wire 1 " Carry $end
$var wire 1 + C6 $end
$var wire 1 , C5 $end
$var wire 1 - C4 $end
$var wire 1 . C3 $end
$var wire 1 / C2 $end
$var wire 1 0 C1 $end
$var wire 1 1 C0 $end
$scope module FA0 $end
$var wire 1 2 A $end
$var wire 1 3 B $end
$var wire 1 % Cin $end
$var wire 1 4 Sum $end
$var wire 1 5 S1 $end
$var wire 1 1 Carry $end
$var wire 1 6 C2 $end
$var wire 1 7 C1 $end
$scope module HA1 $end
$var wire 1 2 A $end
$var wire 1 3 B $end
$var wire 1 5 Sum $end
$var wire 1 7 Carry $end
$scope module AND1 $end
$var wire 1 2 A $end
$var wire 1 3 B $end
$var wire 1 7 F $end
$var wire 1 8 X $end
$upscope $end
$scope module XOR1 $end
$var wire 1 2 A $end
$var wire 1 3 B $end
$var wire 1 5 F $end
$var wire 1 9 X $end
$var wire 1 : Y $end
$var wire 1 ; Z $end
$upscope $end
$upscope $end
$scope module HA2 $end
$var wire 1 5 A $end
$var wire 1 % B $end
$var wire 1 4 Sum $end
$var wire 1 6 Carry $end
$scope module AND1 $end
$var wire 1 5 A $end
$var wire 1 % B $end
$var wire 1 6 F $end
$var wire 1 < X $end
$upscope $end
$scope module XOR1 $end
$var wire 1 5 A $end
$var wire 1 % B $end
$var wire 1 4 F $end
$var wire 1 = X $end
$var wire 1 > Y $end
$var wire 1 ? Z $end
$upscope $end
$upscope $end
$scope module OR1 $end
$var wire 1 7 A $end
$var wire 1 6 B $end
$var wire 1 1 F $end
$var wire 1 @ X $end
$var wire 1 A Y $end
$upscope $end
$upscope $end
$scope module FA1 $end
$var wire 1 B A $end
$var wire 1 C B $end
$var wire 1 1 Cin $end
$var wire 1 D Sum $end
$var wire 1 E S1 $end
$var wire 1 0 Carry $end
$var wire 1 F C2 $end
$var wire 1 G C1 $end
$scope module HA1 $end
$var wire 1 B A $end
$var wire 1 C B $end
$var wire 1 E Sum $end
$var wire 1 G Carry $end
$scope module AND1 $end
$var wire 1 B A $end
$var wire 1 C B $end
$var wire 1 G F $end
$var wire 1 H X $end
$upscope $end
$scope module XOR1 $end
$var wire 1 B A $end
$var wire 1 C B $end
$var wire 1 E F $end
$var wire 1 I X $end
$var wire 1 J Y $end
$var wire 1 K Z $end
$upscope $end
$upscope $end
$scope module HA2 $end
$var wire 1 E A $end
$var wire 1 1 B $end
$var wire 1 D Sum $end
$var wire 1 F Carry $end
$scope module AND1 $end
$var wire 1 E A $end
$var wire 1 1 B $end
$var wire 1 F F $end
$var wire 1 L X $end
$upscope $end
$scope module XOR1 $end
$var wire 1 E A $end
$var wire 1 1 B $end
$var wire 1 D F $end
$var wire 1 M X $end
$var wire 1 N Y $end
$var wire 1 O Z $end
$upscope $end
$upscope $end
$scope module OR1 $end
$var wire 1 G A $end
$var wire 1 F B $end
$var wire 1 0 F $end
$var wire 1 P X $end
$var wire 1 Q Y $end
$upscope $end
$upscope $end
$scope module FA2 $end
$var wire 1 R A $end
$var wire 1 S B $end
$var wire 1 0 Cin $end
$var wire 1 T Sum $end
$var wire 1 U S1 $end
$var wire 1 / Carry $end
$var wire 1 V C2 $end
$var wire 1 W C1 $end
$scope module HA1 $end
$var wire 1 R A $end
$var wire 1 S B $end
$var wire 1 U Sum $end
$var wire 1 W Carry $end
$scope module AND1 $end
$var wire 1 R A $end
$var wire 1 S B $end
$var wire 1 W F $end
$var wire 1 X X $end
$upscope $end
$scope module XOR1 $end
$var wire 1 R A $end
$var wire 1 S B $end
$var wire 1 U F $end
$var wire 1 Y X $end
$var wire 1 Z Y $end
$var wire 1 [ Z $end
$upscope $end
$upscope $end
$scope module HA2 $end
$var wire 1 U A $end
$var wire 1 0 B $end
$var wire 1 T Sum $end
$var wire 1 V Carry $end
$scope module AND1 $end
$var wire 1 U A $end
$var wire 1 0 B $end
$var wire 1 V F $end
$var wire 1 \ X $end
$upscope $end
$scope module XOR1 $end
$var wire 1 U A $end
$var wire 1 0 B $end
$var wire 1 T F $end
$var wire 1 ] X $end
$var wire 1 ^ Y $end
$var wire 1 _ Z $end
$upscope $end
$upscope $end
$scope module OR1 $end
$var wire 1 W A $end
$var wire 1 V B $end
$var wire 1 / F $end
$var wire 1 ` X $end
$var wire 1 a Y $end
$upscope $end
$upscope $end
$scope module FA3 $end
$var wire 1 b A $end
$var wire 1 c B $end
$var wire 1 / Cin $end
$var wire 1 d Sum $end
$var wire 1 e S1 $end
$var wire 1 . Carry $end
$var wire 1 f C2 $end
$var wire 1 g C1 $end
$scope module HA1 $end
$var wire 1 b A $end
$var wire 1 c B $end
$var wire 1 e Sum $end
$var wire 1 g Carry $end
$scope module AND1 $end
$var wire 1 b A $end
$var wire 1 c B $end
$var wire 1 g F $end
$var wire 1 h X $end
$upscope $end
$scope module XOR1 $end
$var wire 1 b A $end
$var wire 1 c B $end
$var wire 1 e F $end
$var wire 1 i X $end
$var wire 1 j Y $end
$var wire 1 k Z $end
$upscope $end
$upscope $end
$scope module HA2 $end
$var wire 1 e A $end
$var wire 1 / B $end
$var wire 1 d Sum $end
$var wire 1 f Carry $end
$scope module AND1 $end
$var wire 1 e A $end
$var wire 1 / B $end
$var wire 1 f F $end
$var wire 1 l X $end
$upscope $end
$scope module XOR1 $end
$var wire 1 e A $end
$var wire 1 / B $end
$var wire 1 d F $end
$var wire 1 m X $end
$var wire 1 n Y $end
$var wire 1 o Z $end
$upscope $end
$upscope $end
$scope module OR1 $end
$var wire 1 g A $end
$var wire 1 f B $end
$var wire 1 . F $end
$var wire 1 p X $end
$var wire 1 q Y $end
$upscope $end
$upscope $end
$scope module FA4 $end
$var wire 1 r A $end
$var wire 1 s B $end
$var wire 1 . Cin $end
$var wire 1 t Sum $end
$var wire 1 u S1 $end
$var wire 1 - Carry $end
$var wire 1 v C2 $end
$var wire 1 w C1 $end
$scope module HA1 $end
$var wire 1 r A $end
$var wire 1 s B $end
$var wire 1 u Sum $end
$var wire 1 w Carry $end
$scope module AND1 $end
$var wire 1 r A $end
$var wire 1 s B $end
$var wire 1 w F $end
$var wire 1 x X $end
$upscope $end
$scope module XOR1 $end
$var wire 1 r A $end
$var wire 1 s B $end
$var wire 1 u F $end
$var wire 1 y X $end
$var wire 1 z Y $end
$var wire 1 { Z $end
$upscope $end
$upscope $end
$scope module HA2 $end
$var wire 1 u A $end
$var wire 1 . B $end
$var wire 1 t Sum $end
$var wire 1 v Carry $end
$scope module AND1 $end
$var wire 1 u A $end
$var wire 1 . B $end
$var wire 1 v F $end
$var wire 1 | X $end
$upscope $end
$scope module XOR1 $end
$var wire 1 u A $end
$var wire 1 . B $end
$var wire 1 t F $end
$var wire 1 } X $end
$var wire 1 ~ Y $end
$var wire 1 !" Z $end
$upscope $end
$upscope $end
$scope module OR1 $end
$var wire 1 w A $end
$var wire 1 v B $end
$var wire 1 - F $end
$var wire 1 "" X $end
$var wire 1 #" Y $end
$upscope $end
$upscope $end
$scope module FA5 $end
$var wire 1 $" A $end
$var wire 1 %" B $end
$var wire 1 - Cin $end
$var wire 1 &" Sum $end
$var wire 1 '" S1 $end
$var wire 1 , Carry $end
$var wire 1 (" C2 $end
$var wire 1 )" C1 $end
$scope module HA1 $end
$var wire 1 $" A $end
$var wire 1 %" B $end
$var wire 1 '" Sum $end
$var wire 1 )" Carry $end
$scope module AND1 $end
$var wire 1 $" A $end
$var wire 1 %" B $end
$var wire 1 )" F $end
$var wire 1 *" X $end
$upscope $end
$scope module XOR1 $end
$var wire 1 $" A $end
$var wire 1 %" B $end
$var wire 1 '" F $end
$var wire 1 +" X $end
$var wire 1 ," Y $end
$var wire 1 -" Z $end
$upscope $end
$upscope $end
$scope module HA2 $end
$var wire 1 '" A $end
$var wire 1 - B $end
$var wire 1 &" Sum $end
$var wire 1 (" Carry $end
$scope module AND1 $end
$var wire 1 '" A $end
$var wire 1 - B $end
$var wire 1 (" F $end
$var wire 1 ." X $end
$upscope $end
$scope module XOR1 $end
$var wire 1 '" A $end
$var wire 1 - B $end
$var wire 1 &" F $end
$var wire 1 /" X $end
$var wire 1 0" Y $end
$var wire 1 1" Z $end
$upscope $end
$upscope $end
$scope module OR1 $end
$var wire 1 )" A $end
$var wire 1 (" B $end
$var wire 1 , F $end
$var wire 1 2" X $end
$var wire 1 3" Y $end
$upscope $end
$upscope $end
$scope module FA6 $end
$var wire 1 4" A $end
$var wire 1 5" B $end
$var wire 1 , Cin $end
$var wire 1 6" Sum $end
$var wire 1 7" S1 $end
$var wire 1 + Carry $end
$var wire 1 8" C2 $end
$var wire 1 9" C1 $end
$scope module HA1 $end
$var wire 1 4" A $end
$var wire 1 5" B $end
$var wire 1 7" Sum $end
$var wire 1 9" Carry $end
$scope module AND1 $end
$var wire 1 4" A $end
$var wire 1 5" B $end
$var wire 1 9" F $end
$var wire 1 :" X $end
$upscope $end
$scope module XOR1 $end
$var wire 1 4" A $end
$var wire 1 5" B $end
$var wire 1 7" F $end
$var wire 1 ;" X $end
$var wire 1 <" Y $end
$var wire 1 =" Z $end
$upscope $end
$upscope $end
$scope module HA2 $end
$var wire 1 7" A $end
$var wire 1 , B $end
$var wire 1 6" Sum $end
$var wire 1 8" Carry $end
$scope module AND1 $end
$var wire 1 7" A $end
$var wire 1 , B $end
$var wire 1 8" F $end
$var wire 1 >" X $end
$upscope $end
$scope module XOR1 $end
$var wire 1 7" A $end
$var wire 1 , B $end
$var wire 1 6" F $end
$var wire 1 ?" X $end
$var wire 1 @" Y $end
$var wire 1 A" Z $end
$upscope $end
$upscope $end
$scope module OR1 $end
$var wire 1 9" A $end
$var wire 1 8" B $end
$var wire 1 + F $end
$var wire 1 B" X $end
$var wire 1 C" Y $end
$upscope $end
$upscope $end
$scope module FA7 $end
$var wire 1 D" A $end
$var wire 1 E" B $end
$var wire 1 + Cin $end
$var wire 1 F" Sum $end
$var wire 1 G" S1 $end
$var wire 1 " Carry $end
$var wire 1 H" C2 $end
$var wire 1 I" C1 $end
$scope module HA1 $end
$var wire 1 D" A $end
$var wire 1 E" B $end
$var wire 1 G" Sum $end
$var wire 1 I" Carry $end
$scope module AND1 $end
$var wire 1 D" A $end
$var wire 1 E" B $end
$var wire 1 I" F $end
$var wire 1 J" X $end
$upscope $end
$scope module XOR1 $end
$var wire 1 D" A $end
$var wire 1 E" B $end
$var wire 1 G" F $end
$var wire 1 K" X $end
$var wire 1 L" Y $end
$var wire 1 M" Z $end
$upscope $end
$upscope $end
$scope module HA2 $end
$var wire 1 G" A $end
$var wire 1 + B $end
$var wire 1 F" Sum $end
$var wire 1 H" Carry $end
$scope module AND1 $end
$var wire 1 G" A $end
$var wire 1 + B $end
$var wire 1 H" F $end
$var wire 1 N" X $end
$upscope $end
$scope module XOR1 $end
$var wire 1 G" A $end
$var wire 1 + B $end
$var wire 1 F" F $end
$var wire 1 O" X $end
$var wire 1 P" Y $end
$var wire 1 Q" Z $end
$upscope $end
$upscope $end
$scope module OR1 $end
$var wire 1 I" A $end
$var wire 1 H" B $end
$var wire 1 " F $end
$var wire 1 R" X $end
$var wire 1 S" Y $end
$upscope $end
$upscope $end
$upscope $end
$upscope $end
$enddefinitions $end
$comment Show the parameter values. $end
$dumpall
$end
#0
$dumpvars
1S"
1R"
1Q"
1P"
1O"
1N"
1M"
1L"
1K"
1J"
0I"
0H"
0G"
0F"
0E"
0D"
1C"
1B"
1A"
1@"
1?"
1>"
1="
1<"
1;"
1:"
09"
08"
07"
06"
05"
04"
13"
12"
11"
10"
1/"
1."
1-"
1,"
1+"
1*"
0)"
0("
0'"
0&"
0%"
0$"
1#"
1""
1!"
1~
1}
1|
1{
1z
1y
1x
0w
0v
0u
0t
0s
0r
1q
1p
1o
1n
1m
1l
1k
1j
1i
1h
0g
0f
0e
0d
0c
0b
1a
1`
1_
1^
1]
1\
1[
1Z
1Y
1X
0W
0V
0U
0T
0S
0R
1Q
1P
1O
1N
1M
1L
1K
1J
1I
1H
0G
0F
0E
0D
0C
0B
1A
1@
1?
1>
1=
1<
1;
1:
19
18
07
06
05
04
03
02
01
00
0/
0.
0-
0,
0+
b0 *
b0 )
b0 (
b0 '
b0 &
0%
b0 $
b0 #
0"
b0 !
$end
#10000
b1 !
b1 *
14
0?
1%
#20000
0>
15
b1 !
b1 *
14
0;
1?
13
0%
b1 $
b1 )
b1 '
#30000
1D
0O
11
0A
b10 !
b10 *
04
16
1>
0<
0=
1?
1%
#40000
0T
1_
00
1Q
1D
0F
1O
01
1L
1M
0N
1A
b10 !
b10 *
04
05
1E
06
1>
1;
0K
1<
1=
03
1C
0%
b10 $
b10 )
b10 '
#50000
b11 !
b11 *
14
0?
1%
#60000
0>
15
b11 !
b11 *
14
0;
1?
13
0%
b11 $
b11 )
b11 '
#70000
1T
0_
10
0Q
0D
1F
1N
0L
0M
1O
11
0A
b100 !
b100 *
04
16
1>
0<
0=
1?
1%
#80000
0d
1o
00
0/
1Q
1a
1T
0F
0V
1_
01
1L
1M
1\
1]
0^
1A
b100 !
b100 *
04
05
0E
1U
06
1>
1;
1K
0[
1<
1=
03
0C
1S
0%
b100 $
b100 )
b100 '
#90000
b101 !
b101 *
14
0?
1%
#100000
0>
15
b101 !
b101 *
14
0;
1?
13
0%
b101 $
b101 )
b101 '
#110000
1D
0O
11
0A
b110 !
b110 *
04
16
1>
0<
0=
1?
1%
#120000
0d
1o
0/
1a
1T
0V
0^
1\
1]
1_
00
1Q
1D
0F
1O
01
1L
1M
0N
1A
b110 !
b110 *
04
05
1E
06
1>
1;
0K
1<
1=
03
1C
0%
b110 $
b110 )
b110 '
#130000
b111 !
b111 *
14
0?
1%
#140000
0>
15
b111 !
b111 *
14
0;
1?
13
0%
b111 $
b111 )
b111 '
#150000
1d
0o
1/
0a
0T
1V
1^
0\
0]
1_
10
0Q
0D
1F
1N
0L
0M
1O
11
0A
b1000 !
b1000 *
04
16
1>
0<
0=
1?
1%
#160000
0t
1!"
00
0/
0.
1Q
1a
0T
1q
1d
0F
0V
1_
0f
1o
01
1L
1M
1\
1]
1l
1m
0n
1A
b1000 !
b1000 *
04
05
0E
0U
1e
06
1>
1;
1K
1[
0k
1<
1=
03
0C
0S
1c
0%
b1000 $
b1000 )
b1000 '
#170000
b1001 !
b1001 *
14
0?
1%
#180000
0>
15
b1001 !
b1001 *
14
0;
1?
13
0%
b1001 $
b1001 )
b1001 '
#190000
1D
0O
11
0A
b1010 !
b1010 *
04
16
1>
0<
0=
1?
1%
#200000
0T
1_
00
1Q
1D
0F
1O
01
1L
1M
0N
1A
b1010 !
b1010 *
04
05
1E
06
1>
1;
0K
1<
1=
03
1C
0%
b1010 $
b1010 )
b1010 '
#210000
b1011 !
b1011 *
14
0?
1%
#220000
0>
15
b1011 !
b1011 *
14
0;
1?
13
0%
b1011 $
b1011 )
b1011 '
#230000
1T
0_
10
0Q
0D
1F
1N
0L
0M
1O
11
0A
b1100 !
b1100 *
04
16
1>
0<
0=
1?
1%
#240000
0t
1!"
0.
1q
1d
0f
0n
1l
1m
1o
00
0/
1Q
1a
1T
0F
0V
1_
01
1L
1M
1\
1]
0^
1A
b1100 !
b1100 *
04
05
0E
1U
06
1>
1;
1K
0[
1<
1=
03
0C
1S
0%
b1100 $
b1100 )
b1100 '
#250000
b1101 !
b1101 *
14
0?
1%
#260000
0>
15
b1101 !
b1101 *
14
0;
1?
13
0%
b1101 $
b1101 )
b1101 '
#270000
1D
0O
11
0A
b1110 !
b1110 *
04
16
1>
0<
0=
1?
1%
#280000
0t
1!"
0.
1q
1d
0f
0n
1l
1m
1o
0/
1a
1T
0V
0^
1\
1]
1_
00
1Q
1D
0F
1O
01
1L
1M
0N
1A
b1110 !
b1110 *
04
05
1E
06
1>
1;
0K
1<
1=
03
1C
0%
b1110 $
b1110 )
b1110 '
#290000
b1111 !
b1111 *
14
0?
1%
#300000
0>
15
b1111 !
b1111 *
14
0;
1?
13
0%
b1111 $
b1111 )
b1111 '
#310000
1t
0!"
1.
0q
0d
1f
1n
0l
0m
1o
1/
0a
0T
1V
1^
0\
0]
1_
10
0Q
0D
1F
1N
0L
0M
1O
11
0A
b10000 !
b10000 *
04
16
1>
0<
0=
1?
1%
#320000
0&"
11"
00
0/
0.
0-
1Q
1a
0T
1q
0d
1#"
1t
0F
0V
1_
0f
1o
0v
1!"
01
1L
1M
1\
1]
1l
1m
1|
1}
0~
1A
b10000 !
b10000 *
04
05
0E
0U
0e
1u
06
1>
1;
1K
1[
1k
0{
1<
1=
03
0C
0S
0c
1s
0%
b10000 $
b10000 )
b10000 '
#330000
b10001 !
b10001 *
14
0?
1%
#340000
0>
15
b10001 !
b10001 *
14
0;
1?
13
0%
b10001 $
b10001 )
b10001 '
#350000
1D
0O
11
0A
b10010 !
b10010 *
04
16
1>
0<
0=
1?
1%
#360000
0T
1_
00
1Q
1D
0F
1O
01
1L
1M
0N
1A
b10010 !
b10010 *
04
05
1E
06
1>
1;
0K
1<
1=
03
1C
0%
b10010 $
b10010 )
b10010 '
#370000
b10011 !
b10011 *
14
0?
1%
#380000
0>
15
b10011 !
b10011 *
14
0;
1?
13
0%
b10011 $
b10011 )
b10011 '
#390000
1T
0_
10
0Q
0D
1F
1N
0L
0M
1O
11
0A
b10100 !
b10100 *
04
16
1>
0<
0=
1?
1%
#400000
0d
1o
00
0/
1Q
1a
1T
0F
0V
1_
01
1L
1M
1\
1]
0^
1A
b10100 !
b10100 *
04
05
0E
1U
06
1>
1;
1K
0[
1<
1=
03
0C
1S
0%
b10100 $
b10100 )
b10100 '
#410000
b10101 !
b10101 *
14
0?
1%
#420000
0>
15
b10101 !
b10101 *
14
0;
1?
13
0%
b10101 $
b10101 )
b10101 '
